bbmapy/__init__.py
bbmapy/_version.py
bbmapy/base.py
bbmapy/commands.py
bbmapy/ex.py
bbmapy/scanner.py
bbmapy-0.0.2.dist-info/LICENSE
bbmapy-0.0.2.dist-info/METADATA
bbmapy-0.0.2.dist-info/WHEEL
bbmapy-0.0.2.dist-info/entry_points.txt
bbmapy-0.0.2.dist-info/top_level.txt
bbmapy-0.0.2.dist-info/RECORD
