Metadata-Version: 2.1
Name: bbmapy
Version: 0.0.2
Summary: A Python wrapper for BBTools
License: 
Project-URL: Homepage, https://github.com/urineri/bbmapy
Project-URL: Repository, https://github.com/urineri/bbmapy.git
Project-URL: BBTools Repository, https://bitbucket.org/berkeleylab/jgi-bbtools/src/master/
Classifier: Development Status :: 3 - Alpha
Classifier: Intended Audience :: Science/Research
Classifier: Programming Language :: Python :: 3.10
Requires-Python: >=3.10
License-File: LICENSE
Requires-Dist: rich>=10.0.0
